Metadata-Version: 2.1
Name: nwpoetry
Version: 1.0.0b101
Summary: Python dependency management and packaging made easy.
Home-page: https://poetry.eustace.io/
License: MIT
Keywords: packaging,dependency,poetry
Author: Sébastien Eustace
Author-email: sebastien@eustace.io
Requires-Python: >=2.7, !=3.0.*, !=3.1.*, !=3.2.*, !=3.3.*
Classifier: License :: OSI Approved :: MIT License
Classifier: Programming Language :: Python :: 2
Classifier: Programming Language :: Python :: 2.7
Classifier: Programming Language :: Python :: 3
Classifier: Programming Language :: Python :: 3.4
Classifier: Programming Language :: Python :: 3.5
Classifier: Programming Language :: Python :: 3.6
Classifier: Programming Language :: Python :: 3.7
Classifier: Programming Language :: Python :: 3.8
Classifier: Topic :: Software Development :: Build Tools
Classifier: Topic :: Software Development :: Libraries :: Python Modules
Requires-Dist: cachecontrol[filecache] (>=0.12.4,<0.13.0)
Requires-Dist: cachy (>=0.3.0,<0.4.0)
Requires-Dist: cleo (>=0.7.6,<0.8.0)
Requires-Dist: clikit (>=0.4.0,<0.5.0)
Requires-Dist: functools32 (>=3.2.3,<4.0.0); python_version >= "2.7" and python_version < "2.8"
Requires-Dist: glob2 (>=0.6,<0.7); python_version >= "2.7" and python_version < "2.8" or python_version >= "3.4" and python_version < "3.5"
Requires-Dist: html5lib (>=1.0,<2.0)
Requires-Dist: importlib-metadata (>=0.23,<0.24); python_version < "3.8"
Requires-Dist: jsonschema (>=3.1,<4.0)
Requires-Dist: keyring (>=18.0,<19.0); python_version >= "2.7" and python_version < "2.8" or python_version >= "3.4" and python_version < "3.5"
Requires-Dist: keyring (>=19.0,<20.0); python_version >= "3.5" and python_version < "4.0"
Requires-Dist: pathlib2 (>=2.3,<3.0); python_version >= "2.7" and python_version < "2.8" or python_version >= "3.4" and python_version < "3.5"
Requires-Dist: pexpect (>=4.7.0,<5.0.0)
Requires-Dist: pkginfo (>=1.4,<2.0)
Requires-Dist: pyparsing (>=2.2,<3.0)
Requires-Dist: pyrsistent (>=0.14.2,<0.15.0)
Requires-Dist: requests (>=2.18,<3.0)
Requires-Dist: requests-toolbelt (>=0.8.0,<0.9.0)
Requires-Dist: shellingham (>=1.1,<2.0)
Requires-Dist: subprocess32 (>=3.5,<4.0); python_version >= "2.7" and python_version < "2.8" or python_version >= "3.4" and python_version < "3.5"
Requires-Dist: tomlkit (>=0.5.8,<0.6.0)
Requires-Dist: typing (>=3.6,<4.0); python_version >= "2.7" and python_version < "2.8" or python_version >= "3.4" and python_version < "3.5"
Requires-Dist: virtualenv (>=16.0,<17.0); python_version >= "2.7" and python_version < "2.8"
Project-URL: Documentation, https://poetry.eustace.io/docs
Project-URL: Repository, https://github.com/sdispater/poetry
